MANIFEST.in
Makefile
README.md
SHELL_README.md
setup.py
cm_api_catch.egg-info/PKG-INFO
cm_api_catch.egg-info/SOURCES.txt
cm_api_catch.egg-info/dependency_links.txt
cm_api_catch.egg-info/entry_points.txt
cm_api_catch.egg-info/requires.txt
cm_api_catch.egg-info/top_level.txt
examples/bulk_config_update.py
examples/cluster_set_up.py
examples/schema.py
examples/timeseries.py
examples/auto-deploy/README.md
examples/auto-deploy/cleanup-master.sh
examples/auto-deploy/clouderaconfig.ini
examples/auto-deploy/deploycloudera.py
examples/auto-deploy/restartcloudera.py
examples/auto-deploy/setup-master.sh
examples/auto-deploy/setup-slave.sh
examples/auto-deploy/stopcloudera.py
src/cm_api/__init__.py
src/cm_api/api_client.py
src/cm_api/http_client.py
src/cm_api/resource.py
src/cm_api/endpoints/__init__.py
src/cm_api/endpoints/batch.py
src/cm_api/endpoints/clusters.py
src/cm_api/endpoints/cms.py
src/cm_api/endpoints/dashboards.py
src/cm_api/endpoints/events.py
src/cm_api/endpoints/host_templates.py
src/cm_api/endpoints/hosts.py
src/cm_api/endpoints/parcels.py
src/cm_api/endpoints/role_config_groups.py
src/cm_api/endpoints/roles.py
src/cm_api/endpoints/services.py
src/cm_api/endpoints/timeseries.py
src/cm_api/endpoints/tools.py
src/cm_api/endpoints/types.py
src/cm_api/endpoints/users.py
src/cm_api_tests/__init__.py
src/cm_api_tests/test_baseapiobject.py
src/cm_api_tests/test_baseapiresource.py
src/cm_api_tests/test_batch.py
src/cm_api_tests/test_clusters.py
src/cm_api_tests/test_cms.py
src/cm_api_tests/test_dashboards.py
src/cm_api_tests/test_events.py
src/cm_api_tests/test_host_template.py
src/cm_api_tests/test_hosts.py
src/cm_api_tests/test_impala.py
src/cm_api_tests/test_replication.py
src/cm_api_tests/test_services.py
src/cm_api_tests/test_snapshot.py
src/cm_api_tests/test_timeseries.py
src/cm_api_tests/test_users.py
src/cm_api_tests/test_yarn.py
src/cm_api_tests/utils.py
src/cm_shell/__init__.py
src/cm_shell/cmps.py
src/cm_shell/prettytable.py