Metadata-Version: 2.1
Name: cm-api-catch
Version: 0.11.0.1
Summary: Cloudera Manager API client
Home-page: http://cloudera.github.com/cm_api/
Author: Cloudera, Inc.
Author-email: scm-users@cloudera.org
License: Apache License 2.0
Platform: UNKNOWN
Classifier: Development Status :: 5 - Production/Stable
Classifier: Operating System :: OS Independent
Classifier: Programming Language :: Python
Classifier: Programming Language :: Python :: 2.6
Classifier: Programming Language :: Python :: 2.7
Classifier: Programming Language :: Python :: 3.3
Provides-Extra: Socks
